odoo/addons/ssi_rma_purchase/README.rst
odoo/addons/ssi_rma_purchase/__init__.py
odoo/addons/ssi_rma_purchase/__manifest__.py
odoo/addons/ssi_rma_purchase/i18n/ssi_rma_purchase.pot
odoo/addons/ssi_rma_purchase/models/__init__.py
odoo/addons/ssi_rma_purchase/models/rma_supplier_line.py
odoo/addons/ssi_rma_purchase/models/stock_rule.py
odoo/addons/ssi_rma_purchase/static/description/icon.png
odoo/addons/ssi_rma_purchase/views/rma_supplier_views.xml
odoo14_addon_ssi_rma_purchase-14.0.1.0.1.dist-info/METADATA
odoo14_addon_ssi_rma_purchase-14.0.1.0.1.dist-info/WHEEL
odoo14_addon_ssi_rma_purchase-14.0.1.0.1.dist-info/top_level.txt
odoo14_addon_ssi_rma_purchase-14.0.1.0.1.dist-info/RECORD
